fastaiapi/__init__.py
fastaiapi-0.0.0.dev0.dist-info/entry_points.txt
fastaiapi-0.0.0.dev0.dist-info/LICENSE
fastaiapi-0.0.0.dev0.dist-info/WHEEL
fastaiapi-0.0.0.dev0.dist-info/METADATA
fastaiapi-0.0.0.dev0.dist-info/RECORD
