Metadata-Version: 2.1
Name: fastaiapi
Version: 0.0.0.dev0
Summary: FastAPI for Artificial Intelligence (AI) Applications
Home-page: https://GitHub.com/FastAIAPI/FastAIAPI
License: MIT
Keywords: FastAPI,Artificial Intelligence,A.I.,AI,application,app
Author: STEAM for Vietnam Foundation AI & Robotics Educational Initiative
Author-email: Edu.AI@STEAMforVietNam.org
Maintainer: STEAM for Vietnam Foundation AI & Robotics Educational Initiative
Maintainer-email: Edu.AI@STEAMforVietNam.org
Requires-Python: >=3.8,<4.0
Classifier: Development Status :: 3 - Alpha
Classifier: Environment :: MacOS X
Classifier: Environment :: Win32 (MS Windows)
Classifier: Framework :: Kedro
Classifier: Intended Audience :: Developers
Classifier: Intended Audience :: Education
Classifier: Intended Audience :: Financial and Insurance Industry
Classifier: Intended Audience :: Healthcare Industry
Classifier: Intended Audience :: Information Technology
Classifier: Intended Audience :: Legal Industry
Classifier: Intended Audience :: Manufacturing
Classifier: Intended Audience :: Science/Research
Classifier: Intended Audience :: System Administrators
Classifier: Intended Audience :: Telecommunications Industry
Classifier: License :: OSI Approved :: MIT License
Classifier: Operating System :: MacOS
Classifier: Operating System :: MacOS :: MacOS X
Classifier: Operating System :: Microsoft
Classifier: Operating System :: Microsoft :: Windows
Classifier: Operating System :: Microsoft :: Windows :: Windows 10
Classifier: Operating System :: Microsoft :: Windows :: Windows 7
Classifier: Operating System :: Microsoft :: Windows :: Windows 8
Classifier: Operating System :: Microsoft :: Windows :: Windows 8.1
Classifier: Operating System :: OS Independent
Classifier: Operating System :: Other OS
Classifier: Operating System :: POSIX
Classifier: Operating System :: POSIX :: Linux
Classifier: Programming Language :: Python
Classifier: Programming Language :: Python :: 3
Classifier: Programming Language :: Python :: 3.10
Classifier: Programming Language :: Python :: 3.11
Classifier: Programming Language :: Python :: 3.8
Classifier: Programming Language :: Python :: 3.9
Classifier: Topic :: Education
Classifier: Topic :: Home Automation
Classifier: Topic :: Scientific/Engineering
Classifier: Topic :: Scientific/Engineering :: Artificial Intelligence
Classifier: Topic :: Scientific/Engineering :: Astronomy
Classifier: Topic :: Scientific/Engineering :: Atmospheric Science
Classifier: Topic :: Scientific/Engineering :: Bio-Informatics
Classifier: Topic :: Scientific/Engineering :: Chemistry
Classifier: Topic :: Scientific/Engineering :: GIS
Classifier: Topic :: Scientific/Engineering :: Human Machine Interfaces
Classifier: Topic :: Scientific/Engineering :: Hydrology
Classifier: Topic :: Scientific/Engineering :: Image Processing
Classifier: Topic :: Scientific/Engineering :: Image Recognition
Classifier: Topic :: Scientific/Engineering :: Information Analysis
Classifier: Topic :: Scientific/Engineering :: Mathematics
Classifier: Topic :: Scientific/Engineering :: Medical Science Apps.
Classifier: Topic :: Scientific/Engineering :: Physics
Classifier: Topic :: Scientific/Engineering :: Visualization
Classifier: Topic :: Software Development
Classifier: Topic :: Software Development :: Libraries
Classifier: Topic :: Software Development :: Libraries :: Application Frameworks
Classifier: Topic :: Software Development :: Libraries :: Python Modules
Provides-Extra: doc
Provides-Extra: lint
Provides-Extra: test
Requires-Dist: ASGIRef
Requires-Dist: Auto-SKLearn (>=0.14.2,<0.15.0)
Requires-Dist: Bayesian-Optimization (>=1.2.0,<2.0.0)
Requires-Dist: CLICK
Requires-Dist: Channels (>=3.0.4,<4.0.0)
Requires-Dist: CloudPickle (>=2.0.0,<3.0.0)
Requires-Dist: Colored (>=1.4.3,<2.0.0)
Requires-Dist: ConfigSpace (>=0.4.20,<0.5.0)
Requires-Dist: CoreAPI (>=2.3.3,<3.0.0)
Requires-Dist: CoreAPI-CLI (>=1.0.9,<2.0.0)
Requires-Dist: Daphne (>=3.0.2,<4.0.0)
Requires-Dist: DataSets (>=1.16.1,<2.0.0)
Requires-Dist: Django-MySQL (>=4.3.0,<5.0.0)
Requires-Dist: FastAPI (>=0.70.1,<0.71.0)
Requires-Dist: GUDHI (>=3.4.1,<4.0.0); python_version < "3.10"
Requires-Dist: GUnicorn (>=20.1.0,<21.0.0)
Requires-Dist: Giotto-TDA (>=0.5.1,<0.6.0); python_version < "3.10"
Requires-Dist: GitPython (>=3.1.24,<4.0.0)
Requires-Dist: Google-Cloud-Translate (>=3.6.1,<4.0.0)
Requires-Dist: GoogleTrans (>=4.0.0rc1,<5.0.0)
Requires-Dist: GraphQL-Core (>=3.1.6,<4.0.0)
Requires-Dist: GraphQL-Relay (>=3.1.0,<4.0.0)
Requires-Dist: GraphQLClient (>=0.2.4,<0.3.0)
Requires-Dist: Graphene (>=3.0,<4.0)
Requires-Dist: HAL-Codec (>=1.0.2,<2.0.0)
Requires-Dist: HTTPie (>=2.6.0,<3.0.0)
Requires-Dist: Hpbandster (>=0.7.4,<0.8.0)
Requires-Dist: HuggingFace-Hub (>=0.2.1,<0.3.0)
Requires-Dist: Hypercorn (>=0.12.0,<0.13.0)
Requires-Dist: JSONHyperSchema-Codec (>=1.0.3,<2.0.0)
Requires-Dist: JSONSchema (>=4.2.1,<5.0.0)
Requires-Dist: JobLib (>=1.1.0,<2.0.0)
Requires-Dist: Kedro (>=0.17.5,<0.18.0); python_version < "3.9"
Requires-Dist: LIME (>=0.2.0.1,<0.3.0.0)
Requires-Dist: MariaDB-DynCol (>=3.4.0,<4.0.0)
Requires-Dist: Markdown (>=3.3.6,<4.0.0)
Requires-Dist: MySQL-Connector-Python (>=8.0.27,<9.0.0)
Requires-Dist: MySQLClient (>=2.1.0,<3.0.0)
Requires-Dist: NumBa
Requires-Dist: NumPy
Requires-Dist: OpenAPI-Codec (>=1.3.2,<2.0.0)
Requires-Dist: PSUtil (>=5.8.0,<6.0.0)
Requires-Dist: Pandas (>=1.3.4,<2.0.0)
Requires-Dist: Pillow (>=8.4.0,<9.0.0)
Requires-Dist: PsycoPG2-binary (>=2.9.2,<3.0.0)
Requires-Dist: Py-GQL (>=0.6.1,<0.7.0)
Requires-Dist: PyArrow (>=6.0.1,<7.0.0)
Requires-Dist: PySpark (>=3.2.0,<4.0.0)
Requires-Dist: PyTZ (>=2021.3,<2022.0)
Requires-Dist: Pydantic (>=1.8.2,<2.0.0)
Requires-Dist: Python-DateUtil
Requires-Dist: Python-DotEnv (>=0.19.2,<0.20.0)
Requires-Dist: Quart (>=0.16.1,<0.17.0)
Requires-Dist: Ray (>=1.9.0,<2.0.0); python_version < "3.10"
Requires-Dist: Requests
Requires-Dist: Ruamel.YAML (>=0.17.17,<0.18.0)
Requires-Dist: S3FS (>=2021.11.1,<2022.0.0)
Requires-Dist: SGQLC (>=14.1,<15.0)
Requires-Dist: SHAP (>=0.40.0,<0.41.0); python_version < "3.10"
Requires-Dist: SQLAlchemy (>=1.4.28,<2.0.0)
Requires-Dist: SQLModel (>=0.0.5,<0.0.6)
Requires-Dist: SciKit-Fuzzy (>=0.4.2,<0.5.0)
Requires-Dist: SciKit-Image (>=0.19.0,<0.20.0)
Requires-Dist: SciKit-Learn
Requires-Dist: SciPy
Requires-Dist: SentencePiece (>=0.1.96,<0.2.0)
Requires-Dist: Starlette
Requires-Dist: StatsModels (>=0.13.1,<0.14.0)
Requires-Dist: TIMM (>=0.4.12,<0.5.0); python_version < "3.10"
Requires-Dist: Tabulate (>=0.8.9,<0.9.0)
Requires-Dist: TensorFlow (>=2.7.0,<3.0.0); python_version < "3.10"
Requires-Dist: TensorFlow-DataSets (>=4.4.0,<5.0.0)
Requires-Dist: TensorFlow-Hub (>=0.12.0,<0.13.0)
Requires-Dist: Torch (>=1.10.0,<2.0.0); python_version < "3.10"
Requires-Dist: Torch-Model-Archiver (>=0.5.0,<0.6.0)
Requires-Dist: TorchAudio (>=0.10.0,<0.11.0); python_version < "3.10"
Requires-Dist: TorchServe (>=0.5.0,<0.6.0)
Requires-Dist: TorchText (>=0.11.0,<0.12.0); python_version < "3.10"
Requires-Dist: TorchVision (>=0.11.1,<0.12.0); python_version < "3.10"
Requires-Dist: Tqdm (>=4.62.3,<5.0.0)
Requires-Dist: Transformers (>=4.12.5,<5.0.0); python_version < "3.10"
Requires-Dist: Uvicorn (>=0.16.0,<0.17.0)
Project-URL: Documentation, https://FastAIAPI.GitHub.io/FastAIAPI
Project-URL: GitHub, https://GitHub.com/FastAIAPI/FastAIAPI
Project-URL: Repository, https://GitHub.com/FastAIAPI/FastAIAPI
